S3Dict/__init__.py
s3dictionary/__init__.py
S3Dictionary-0.13.dist-info/LICENSE
S3Dictionary-0.13.dist-info/METADATA
S3Dictionary-0.13.dist-info/WHEEL
S3Dictionary-0.13.dist-info/top_level.txt
S3Dictionary-0.13.dist-info/RECORD
