Metadata-Version: 2.1
Name: S3Dictionary
Version: 0.13
Summary: python dictionary class providing persistent storage by serializing state to a json file on an Amazon S3 bucket
Home-page: https://github.com/RhetTbull/
Author: Rhet Turnbull
Author-email: rturnbull+git@gmail.com
License: License :: OSI Approved :: MIT License
Download-URL: https://github.com/RhetTbull/s3dict
Project-URL: GitHub, https://github.com/RhetTbull/s3dict
Platform: UNKNOWN
Classifier: Development Status :: 4 - Beta
Classifier: Intended Audience :: Developers
Classifier: License :: OSI Approved :: MIT License
Classifier: Programming Language :: Python
Classifier: Topic :: Software Development :: Libraries :: Python Modules
Requires-Dist: boto3
